simple_math_moh/__init__.py
simple_math_moh/operations.py
simple_math_moh-1.0.dist-info/METADATA
simple_math_moh-1.0.dist-info/WHEEL
simple_math_moh-1.0.dist-info/top_level.txt
simple_math_moh-1.0.dist-info/RECORD
