Metadata-Version: 2.4
Name: simple_math_moh
Version: 1.0
Summary: A simple math package for beginners (add, multiply, divide)
Author: Mohamed Adam
Author-email: mohan223@gmail.com
Dynamic: author
Dynamic: author-email
Dynamic: summary
